gpiozero/__init__.py
gpiozero/boards.py
gpiozero/compat.py
gpiozero/devices.py
gpiozero/exc.py
gpiozero/input_devices.py
gpiozero/internal_devices.py
gpiozero/mixins.py
gpiozero/output_devices.py
gpiozero/spi_devices.py
gpiozero/threads.py
gpiozero/tones.py
gpiozero/tools.py
gpiozero/pins/__init__.py
gpiozero/pins/data.py
gpiozero/pins/local.py
gpiozero/pins/mock.py
gpiozero/pins/native.py
gpiozero/pins/pi.py
gpiozero/pins/pigpio.py
gpiozero/pins/rpigpio.py
gpiozero/pins/rpio.py
gpiozero/pins/spi.py
gpiozerocli/__init__.py
gpiozerocli/pinout.py
gpiozero_ha-1.5.3.dist-info/LICENSE.rst
gpiozero_ha-1.5.3.dist-info/METADATA
gpiozero_ha-1.5.3.dist-info/WHEEL
gpiozero_ha-1.5.3.dist-info/entry_points.txt
gpiozero_ha-1.5.3.dist-info/top_level.txt
gpiozero_ha-1.5.3.dist-info/RECORD
